demosys/__init__.py
demosys/exceptions.py
demosys/conf/__init__.py
demosys/conf/default.py
demosys/context/__init__.py
demosys/context/base.py
demosys/context/headless.py
demosys/context/glfw/__init__.py
demosys/context/glfw/keys.py
demosys/context/glfw/window.py
demosys/context/pyglet/__init__.py
demosys/context/pyglet/keys.py
demosys/context/pyglet/window.py
demosys/context/pyqt/__init__.py
demosys/context/pyqt/keys.py
demosys/context/pyqt/window.py
demosys/context/sdl2/__init__.py
demosys/context/sdl2/keys.py
demosys/context/sdl2/window.py
demosys/effect_templates/cube_simple/dependencies.py
demosys/effect_templates/cube_simple/effects.py
demosys/effect_templates/cube_simple/resources/programs/cube_simple/cube_plain.glsl
demosys/effect_templates/empty/dependencies.py
demosys/effect_templates/empty/effects.py
demosys/effect_templates/raymarching_simple/dependencies.py
demosys/effect_templates/raymarching_simple/effects.py
demosys/effect_templates/raymarching_simple/resources/programs/raymarching_simple/raymarching_simple.glsl
demosys/effects/__init__.py
demosys/effects/effect.py
demosys/effects/registry.py
demosys/effects/deferred/dependencies.py
demosys/effects/deferred/effects.py
demosys/effects/deferred/resources/programs/deferred/combine.glsl
demosys/effects/deferred/resources/programs/deferred/debug.glsl
demosys/effects/deferred/resources/programs/deferred/geometry_color.glsl
demosys/effects/deferred/resources/programs/deferred/geometry_texture.glsl
demosys/effects/deferred/resources/programs/deferred/light_point.glsl
demosys/effects/text/dependencies.py
demosys/effects/text/effects/__init__.py
demosys/effects/text/effects/base.py
demosys/effects/text/effects/renderer_2d.py
demosys/effects/text/effects/writer_2d.py
demosys/effects/text/resources/data/demosys/text/meta.json
demosys/effects/text/resources/programs/demosys/text/textwriter2d.glsl
demosys/effects/text/resources/programs/demosys/text/view_renderer_texture.glsl
demosys_py-2.1.1.dist-info/LICENSE.txt
demosys_py-2.1.1.dist-info/METADATA
demosys_py-2.1.1.dist-info/WHEEL
demosys_py-2.1.1.dist-info/entry_points.txt
demosys_py-2.1.1.dist-info/top_level.txt
demosys_py-2.1.1.dist-info/RECORD
