Metadata-Version: 2.1
Name: demosys-py
Version: 2.1.1
Summary: Modern OpenGL 3.3+ Framework inspired by Django
Home-page: https://github.com/Contraz/demosys-py
Author: Einar Forselv
Author-email: eforselv@gmail.com
Maintainer: Einar Forselv
Maintainer-email: eforselv@gmail.com
License: UNKNOWN
Keywords: opengl,framework,demoscene
Platform: UNKNOWN
Classifier: Programming Language :: Python
Classifier: Environment :: MacOS X
Classifier: Environment :: X11 Applications
Classifier: Intended Audience :: Developers
Classifier: Topic :: Multimedia :: Graphics
Classifier: License :: OSI Approved :: ISC License (ISCL)
Classifier: Programming Language :: Python :: 3
Classifier: Programming Language :: Python :: 3.6
Classifier: Programming Language :: Python :: 3.7
Classifier: Topic :: Software Development :: Libraries :: Application Frameworks
Requires-Dist: moderngl (==5.5.2)
Requires-Dist: pyrr (>=0.10)
Requires-Dist: Pillow (>=5)
Requires-Dist: pyrocket (==0.2.8)
Requires-Dist: PyWavefront (==1.0.4)
Requires-Dist: PyQt5 (>=5.12)
Requires-Dist: trimesh (>=2.38)
Provides-Extra: pysdl2
Requires-Dist: PySDL2 (==0.9.6) ; extra == 'pysdl2'
Provides-Extra: glfw
Requires-Dist: glfw (==1.7.0) ; extra == 'glfw'
Provides-Extra: pyglet
Requires-Dist: pyglet (==1.3.2) ; extra == 'pyglet'
Provides-Extra: python-vlc
Requires-Dist: python-vlc (==3.0.102) ; extra == 'python-vlc'
